sphinxcontrib/__init__.py
sphinxcontrib/programoutput/__init__.py
sphinxcontrib/programoutput/ansi.py
sphinxcontrib/programoutput/black-on-white.css
sphinxcontrib/programoutput/tests/__init__.py
sphinxcontrib/programoutput/tests/test_ansi.py
sphinxcontrib/programoutput/tests/test_cache.py
sphinxcontrib/programoutput/tests/test_command.py
sphinxcontrib/programoutput/tests/test_directive.py
sphinxcontrib/programoutput/tests/test_setup.py
sphinxcontrib/programoutput/tests/test_util.py
sphinxcontrib_programoutput2-2.0a1.dist-info/LICENSE
sphinxcontrib_programoutput2-2.0a1.dist-info/METADATA
sphinxcontrib_programoutput2-2.0a1.dist-info/WHEEL
sphinxcontrib_programoutput2-2.0a1.dist-info/top_level.txt
sphinxcontrib_programoutput2-2.0a1.dist-info/RECORD
