Metadata-Version: 2.1
Name: sphinxcontrib-programoutput2
Version: 2.0a1
Summary: Sphinx extension to include program output
Home-page: https://sphinxcontrib-programoutput2.readthedocs.org/
Author: Sebastian Wiesner
Author-email: lunaryorn@gmail.com
Maintainer: Sorin Sbarnea
Maintainer-email: sorin.sbarnea@gmail.com
License: BSD
Project-URL: Bug Tracker, https://github.com/sphinx-contrib/sphinxcontrib-programoutput/issues
Project-URL: CI: GitHub, https://github.com/sphinx-contrib/sphinxcontrib-programoutput/actions?query=workflow:gh+branch:master+event:push
Project-URL: Documentation, https://sphinxcontrib-programoutput2.readthedocs.org/
Project-URL: Source Code, https://github.com/sphinx-contrib/sphinxcontrib-programoutput
Keywords: sphinx,cli,command,output,program,example
Platform: UNKNOWN
Classifier: Development Status :: 5 - Production/Stable
Classifier: Intended Audience :: Developers
Classifier: License :: OSI Approved :: BSD License
Classifier: Operating System :: OS Independent
Classifier: Programming Language :: Python
Classifier: Programming Language :: Python :: 3
Classifier: Programming Language :: Python :: 3.6
Classifier: Programming Language :: Python :: 3.7
Classifier: Programming Language :: Python :: 3.8
Classifier: Programming Language :: Python :: 3.9
Classifier: Programming Language :: Python :: Implementation :: CPython
Classifier: Topic :: Documentation
Classifier: Topic :: Utilities
Classifier: Framework :: Sphinx
Classifier: Framework :: Sphinx :: Extension
Provides: sphinxcontrib.programoutput
Requires-Python: >=3.6
Requires-Dist: Sphinx (>=1.7.0)
Provides-Extra: test
Requires-Dist: coverage (>=5.3.1) ; extra == 'test'
Requires-Dist: mock ; extra == 'test'
Requires-Dist: pytest ; extra == 'test'
